wil_cliff/__init__.py
wil_cliff/wil_cliff.py
wil_cliff-1.1.0.dist-info/LICENSE
wil_cliff-1.1.0.dist-info/METADATA
wil_cliff-1.1.0.dist-info/WHEEL
wil_cliff-1.1.0.dist-info/RECORD
